sportbot/__init__.py
sportbot/bell.wav
sportbot/bot.py
sportbot/exercice.py
sportbot/helpers.py
sportbot/main.py
sportbot/screen.py
sportbot/sequence.py
sportbot/sound.py
sportbot/tts/10-push-ups.mp3
sportbot/tts/alternate-lunges.mp3
sportbot/tts/backward-lunges.mp3
sportbot/tts/burpees.mp3
sportbot/tts/chair.mp3
sportbot/tts/crunchs.mp3
sportbot/tts/double-ended-bag-boxing.mp3
sportbot/tts/forward-lunges.mp3
sportbot/tts/heels-rise.mp3
sportbot/tts/heels-to-buttocks.mp3
sportbot/tts/jab-cross.mp3
sportbot/tts/jump-squats.mp3
sportbot/tts/jumping-jacks.mp3
sportbot/tts/knee-kicks.mp3
sportbot/tts/knees-rise.mp3
sportbot/tts/left-right-hooks.mp3
sportbot/tts/left-right-uppercuts.mp3
sportbot/tts/maintain.mp3
sportbot/tts/mountain-climber.mp3
sportbot/tts/plank.mp3
sportbot/tts/prepare.mp3
sportbot/tts/push-up.mp3
sportbot/tts/rest.mp3
sportbot/tts/shadow-boxing.mp3
sportbot/tts/squats.mp3
sportbot/tts/twists.mp3
sportbot-0.1.0.dist-info/entry_points.txt
sportbot-0.1.0.dist-info/WHEEL
sportbot-0.1.0.dist-info/METADATA
sportbot-0.1.0.dist-info/RECORD
