Metadata-Version: 2.1
Name: sportbot
Version: 0.1.0
Summary: 
Author: Adrien Pensart
Author-email: adrien.pensart@corp.ovh.com
Requires-Python: >=3.8,<4.0
Classifier: Programming Language :: Python :: 3
Classifier: Programming Language :: Python :: 3.8
Classifier: Programming Language :: Python :: 3.9
Requires-Dist: asciimatics (>=1.13.0,<2.0.0)
Requires-Dist: colorama (>=0.4.4,<0.5.0)
Requires-Dist: gTTS (>=2.2.2,<3.0.0)
Requires-Dist: python-slugify (>=4.0.1,<5.0.0)
Requires-Dist: python-vlc (>=3.0.12118,<4.0.0)
